imgtoolkit/__init__.py
imgtoolkit/tools.py
imgtoolkit-0.1.3.dist-info/licenses/LICENSE
imgtoolkit-0.1.3.dist-info/METADATA
imgtoolkit-0.1.3.dist-info/WHEEL
imgtoolkit-0.1.3.dist-info/entry_points.txt
imgtoolkit-0.1.3.dist-info/top_level.txt
imgtoolkit-0.1.3.dist-info/RECORD
