Metadata-Version: 2.4
Name: imgtoolkit
Version: 0.1.3
Summary: Collection of image tools for checking photos for blur and duplicates, and handle fake PNG transparency
Home-page: https://github.com/shivanraptor/imgtoolkit
Author: Raptor K
Author-email: findme@raptor.hk
Keywords: image,find duplicate,find blur,fake png
Classifier: Development Status :: 4 - Beta
Classifier: Intended Audience :: Developers
Classifier: Programming Language :: Python :: 3
Classifier: Operating System :: MacOS :: MacOS X
Classifier: Operating System :: Microsoft :: Windows
Classifier: License :: OSI Approved :: MIT License
Requires-Python: >3.8.0
License-File: LICENSE
Requires-Dist: dhash
Requires-Dist: alive-progress
Requires-Dist: Pillow
Requires-Dist: opencv-python
Requires-Dist: about-time
Requires-Dist: grapheme
Dynamic: author
Dynamic: author-email
Dynamic: classifier
Dynamic: description
Dynamic: home-page
Dynamic: keywords
Dynamic: license-file
Dynamic: requires-dist
Dynamic: requires-python
Dynamic: summary
